rtdicomtools/__init__.py
rtdicomtools/dcmMLC.py
rtdicomtools/dcmStructureSet.py
rtdicomtools/npViewer3D.py
rtdicomtools-1.0.1.dist-info/LICENSE
rtdicomtools-1.0.1.dist-info/METADATA
rtdicomtools-1.0.1.dist-info/WHEEL
rtdicomtools-1.0.1.dist-info/top_level.txt
rtdicomtools-1.0.1.dist-info/RECORD
