Metadata-Version: 2.1
Name: rtdicomtools
Version: 1.0.1
Home-page: https://github.com/sebasj13/RTDICOMTools
Author: Sebastian Schäfer
Author-email: se.schaefer@uke.de
Project-URL: Bug Tracker, https://github.com/sebasj13/RTDICOMTools/issues
Keywords: medical,physics,DICOM,radiotherapy,3D numpy viewer,RTPLAN,RTSTRUCT
Classifier: Programming Language :: Python :: 3
Classifier: License :: OSI Approved :: MIT License
Classifier: Operating System :: OS Independent
Requires-Python: >=3.8
License-File: LICENSE
Requires-Dist: numpy
Requires-Dist: opencv-python
Requires-Dist: Pillow
Requires-Dist: matplotlib
Requires-Dist: pandas
Requires-Dist: pydicom
Requires-Dist: customtkinter
